abmax/__init__.py
abmax/functions.py
abmax/functions_extensive.py
abmax/structs.py
abmax/contexts/finance/algorithms.py
abmax/contexts/foraging/__init__.py
abmax/contexts/foraging/functions.py
abmax/contexts/foraging/structs.py
abmax/contexts/predation/algorithms.py
abmax/contexts/traffic/algorithms.py
abmax/space/__init__.py
abmax/space/continuous/__init__.py
abmax/space/continuous/functions.py
abmax/space/continuous/structs.py
abmax-0.0.5.dist-info/METADATA
abmax-0.0.5.dist-info/WHEEL
abmax-0.0.5.dist-info/licenses/LICENSE.md
abmax-0.0.5.dist-info/RECORD
