Metadata-Version: 2.4
Name: abmax
Version: 0.0.5
Summary: ABM package in JAX.
Author-email: Siddharth Chaturvedi <sidchat.sc@gmail.com>
License: MIT License
License-File: LICENSE.md
Keywords: ABM,Agent-Based-Modeling,abm,abmax,agent-based-modeling,jax,simulation
Classifier: Development Status :: 3 - Alpha
Classifier: Intended Audience :: Developers
Classifier: License :: OSI Approved :: MIT License
Classifier: Natural Language :: English
Classifier: Programming Language :: Python :: 3
Classifier: Topic :: Scientific/Engineering :: Artificial Intelligence
Requires-Python: >=3.9.0
Requires-Dist: flax>=0.7.4
Requires-Dist: jax>=0.4.13
